hydenmj/__init__.py
hydenmj/main.py
hydenmj-0.1.1.dist-info/METADATA
hydenmj-0.1.1.dist-info/WHEEL
hydenmj-0.1.1.dist-info/entry_points.txt
hydenmj-0.1.1.dist-info/top_level.txt
hydenmj-0.1.1.dist-info/RECORD
